LICENSE
MANIFEST.in
README.rst
setup.cfg
setup.py
mezzanine_slideshows/__init__.py
mezzanine_slideshows/admin.py
mezzanine_slideshows/context_processors.py
mezzanine_slideshows/models.py
mezzanine_slideshows/tests.py
mezzanine_slideshows/views.py
mezzanine_slideshows.egg-info/PKG-INFO
mezzanine_slideshows.egg-info/SOURCES.txt
mezzanine_slideshows.egg-info/dependency_links.txt
mezzanine_slideshows.egg-info/top_level.txt
mezzanine_slideshows/migrations/0001_initial.py
mezzanine_slideshows/migrations/__init__.py
mezzanine_slideshows/migrations/__pycache__/0001_initial.cpython-34.pyc
mezzanine_slideshows/migrations/__pycache__/__init__.cpython-34.pyc
mezzanine_slideshows/static/mezzanine-slideshows/css/owl.carousel.css
mezzanine_slideshows/static/mezzanine-slideshows/css/owl.theme.css
mezzanine_slideshows/static/mezzanine-slideshows/js/jquery.magnific-popup.js
mezzanine_slideshows/static/mezzanine-slideshows/js/owl.carousel.js
mezzanine_slideshows/templates/base.html
mezzanine_slideshows/templates/includes/mezzanine_slideshows.html