Metadata-Version: 1.1
Name: mezzanine-slideshows
Version: 0.3.0
Summary: A simple mezzanine app which allows the placement of a Mezzanine Gallery within another Mezzanine Page as a slideshow
Home-page: https://github.com/philipsouthwell/mezzanine-slideshows
Author: Philip Southwell
Author-email: phil@zoothink.com
License: BSD License
Keywords: django,mezzanine
Platform: UNKNOWN
Classifier: Environment :: Web Environment
Classifier: Intended Audience :: Developers
Classifier: License :: OSI Approved :: BSD License
Classifier: Operating System :: OS Independent
Classifier: Programming Language :: Python
Classifier: Programming Language :: Python :: 3
Classifier: Programming Language :: Python :: 3.2
Classifier: Programming Language :: Python :: 3.3
Classifier: Topic :: Internet :: WWW/HTTP
Classifier: Topic :: Internet :: WWW/HTTP :: Dynamic Content
